{
    "fluentMethods": true,
    "relationships": [
        {
            "relationshipName": "product",
            "otherEntityName": "product",
            "relationshipType": "many-to-one",
            "otherEntityField": "id"
        },
        {
            "relationshipType": "one-to-many",
            "relationshipName": "product",
            "otherEntityName": "product",
            "otherEntityRelationshipName": "product"
        },
        {
            "relationshipType": "one-to-many",
            "relationshipName": "description",
            "otherEntityName": "productDescription",
            "otherEntityRelationshipName": "product"
        },
        {
            "relationshipType": "one-to-many",
            "relationshipName": "image",
            "otherEntityName": "picture",
            "otherEntityRelationshipName": "product"
        },
        {
            "relationshipType": "many-to-one",
            "relationshipName": "category",
            "otherEntityName": "category",
            "otherEntityField": "id"
        },
        {
            "relationshipType": "many-to-many",
            "relationshipName": "supplier",
            "otherEntityName": "supplier",
            "ownerSide": false,
            "otherEntityRelationshipName": "product"
        },
        {
            "relationshipName": "shopingCart",
            "otherEntityName": "shopingCart",
            "relationshipType": "many-to-one",
            "otherEntityField": "id"
        },
        {
            "relationshipName": "promotion",
            "otherEntityName": "promotion",
            "relationshipType": "many-to-one",
            "otherEntityField": "id"
        }
    ],
    "fields": [
        {
            "fieldName": "returnAuthorization",
            "fieldType": "Boolean"
        },
        {
            "fieldName": "name",
            "fieldType": "String",
            "fieldValidateRules": [
                "required"
            ]
        },
        {
            "fieldName": "price",
            "fieldType": "Double",
            "fieldValidateRules": [
                "required"
            ]
        },
        {
            "fieldName": "size",
            "fieldType": "String"
        },
        {
            "fieldName": "color",
            "fieldType": "String",
            "fieldValidateRules": [
                "required"
            ]
        },
        {
            "fieldName": "description",
            "fieldType": "String",
            "fieldValidateRules": [
                "required"
            ]
        },
        {
            "fieldName": "otherDetails",
            "fieldType": "String"
        }
    ],
    "changelogDate": "20161026162654",
    "entityTableName": "product",
    "dto": "no",
    "pagination": "pager",
    "service": "serviceImpl"
}